{
  "generatedAt": "2026-06-03T06:30:14.507Z",
  "regime": "BEAR",
  "rows": [
    {
      "symbol": "SSWL",
      "direction": "BUY",
      "pattern": "REBOUND",
      "conviction": 73,
      "ltp": 209.85,
      "entryPrice": 208.15,
      "stopLoss": 191.03,
      "target1": 228.97,
      "target1Date": "2026-06-10",
      "target2": 249.78,
      "target2Date": "2026-06-19",
      "target3": 274.76,
      "target3Date": "2026-07-01",
      "riskReward": 1.22,
      "shareholdingNote": "FII 8.2%↓ · DII 5.1%↑ · P 61.1%→ · Pledge 0.0% · MC ₹3.3KCr",
      "vol5dRatio": 1.42,
      "smartMoneyUp": false,
      "fiiDelta": -0.11,
      "promoterDelta": 0,
      "diiDelta": 0.37
    }
  ]
}